AUTHORS
CHANGES.txt
COPYING
MANIFEST.in
README.txt
setup.py
yaco/__init__.py
yaco.hghooks.egg-info/PKG-INFO
yaco.hghooks.egg-info/SOURCES.txt
yaco.hghooks.egg-info/dependency_links.txt
yaco.hghooks.egg-info/entry_points.txt
yaco.hghooks.egg-info/namespace_packages.txt
yaco.hghooks.egg-info/not-zip-safe
yaco.hghooks.egg-info/requires.txt
yaco.hghooks.egg-info/top_level.txt
yaco/hghooks/__init__.py