Metadata-Version: 1.0
Name: yaco.hghooks
Version: 0.1.2
Summary: Extensions to hghooks used at Yaco Sistemas
Home-page: http://bitbucket.org/lgs/yaco.hghooks
Author: Lorenzo Gil Sanchez
Author-email: lgs@yaco.es
License: LGPL 3
Keywords: mercurial hooks trac yaco
Platform: UNKNOWN
